tuxmake/__init__.py
tuxmake/__main__.py
tuxmake/arch.py
tuxmake/build.py
tuxmake/build_utils.py
tuxmake/cache.py
tuxmake/cli.py
tuxmake/cmdline.py
tuxmake/config.py
tuxmake/deprecated.py
tuxmake/exceptions.py
tuxmake/log.py
tuxmake/logging.py
tuxmake/metadata.pl
tuxmake/metadata.py
tuxmake/output.py
tuxmake/runtime.py
tuxmake/target.py
tuxmake/toolchain.py
tuxmake/utils.py
tuxmake/wrapper.py
tuxmake/xdg.py
tuxmake/arch/aarch64.ini
tuxmake/arch/alpha.ini
tuxmake/arch/amd64.ini
tuxmake/arch/arc.ini
tuxmake/arch/arm.ini
tuxmake/arch/arm64.ini
tuxmake/arch/armel.ini
tuxmake/arch/armhf.ini
tuxmake/arch/armv5.ini
tuxmake/arch/armv8l.ini
tuxmake/arch/csky.ini
tuxmake/arch/hexagon.ini
tuxmake/arch/i386.ini
tuxmake/arch/i686.ini
tuxmake/arch/loongarch.ini
tuxmake/arch/loongarch64.ini
tuxmake/arch/m68k.ini
tuxmake/arch/microblaze.ini
tuxmake/arch/mips.ini
tuxmake/arch/mips64.ini
tuxmake/arch/nios2.ini
tuxmake/arch/openrisc.ini
tuxmake/arch/parisc.ini
tuxmake/arch/powerpc.ini
tuxmake/arch/riscv.ini
tuxmake/arch/riscv32.ini
tuxmake/arch/riscv64.ini
tuxmake/arch/s390.ini
tuxmake/arch/s390x.ini
tuxmake/arch/sh.ini
tuxmake/arch/sh2.ini
tuxmake/arch/sh4.ini
tuxmake/arch/sparc.ini
tuxmake/arch/sparc64.ini
tuxmake/arch/um.ini
tuxmake/arch/x86_64.ini
tuxmake/arch/xtensa.ini
tuxmake/metadata/artifacts.ini
tuxmake/metadata/ccache.ini
tuxmake/metadata/compiler.ini
tuxmake/metadata/git.ini
tuxmake/metadata/hardware.ini
tuxmake/metadata/os.ini
tuxmake/metadata/resources.ini
tuxmake/metadata/sccache.ini
tuxmake/metadata/source.ini
tuxmake/metadata/system_map.ini
tuxmake/metadata/tools.ini
tuxmake/metadata/uname.ini
tuxmake/metadata/vmlinux.ini
tuxmake/runtime/docker-local.ini
tuxmake/runtime/docker.ini
tuxmake/runtime/null.ini
tuxmake/runtime/podman-local.ini
tuxmake/runtime/podman.ini
tuxmake/runtime/bin/tuxmake-check-environment
tuxmake/runtime/bin/tuxmake-download-all-korg-toolchains
tuxmake/runtime/bin/tuxmake-prepare-korg-gcc
tuxmake/runtime/bin/tuxmake-run-offline
tuxmake-1.34.0.dist-info/entry_points.txt
tuxmake-1.34.0.dist-info/LICENSE
tuxmake-1.34.0.dist-info/WHEEL
tuxmake-1.34.0.dist-info/METADATA
tuxmake-1.34.0.dist-info/RECORD
