Metadata-Version: 2.1
Name: tuxmake
Version: 1.34.0
Summary: Thin wrapper to build Linux kernels
Home-page: https://tuxmake.org/
Author: Antonio Terceiro
Author-email: antonio.terceiro@linaro.org
Requires-Python: >=3.6
Classifier: License :: OSI Approved :: MIT License
